dict_schema_validator/__init__.py
dict_schema_validator/validator.py
dict_schema_validator-0.2.0.dist-info/LICENSE
dict_schema_validator-0.2.0.dist-info/METADATA
dict_schema_validator-0.2.0.dist-info/WHEEL
dict_schema_validator-0.2.0.dist-info/top_level.txt
dict_schema_validator-0.2.0.dist-info/RECORD
