Metadata-Version: 2.1
Name: dict-schema-validator
Version: 0.2.0
Summary: Validate python dictionaries (mongodb docs etc) using a JSON schema
Home-page: https://github.com/andrey-ushakov/dict-schema-validator
Author: Andrey U
License: UNKNOWN
Platform: UNKNOWN
Classifier: Programming Language :: Python :: 3
Classifier: License :: OSI Approved :: BSD License
Classifier: Operating System :: OS Independent
Requires-Python: >=3.6
